<?xml version="1.0" encoding="utf-8" ?>
<Objects>
  <Object type="1" id="9" name="Broad Sword">
    <Texture x ="0" y="0">
      <FileName>itemsEmbed</FileName>
      <Animated />
    </Texture>
  </Object>
  <Object type="1" id="10" name="Iron Sword">
    <Texture x ="1" y="0">
      <FileName>itemsEmbed</FileName>
      <Animated />
    </Texture>
  </Object>
  <Object type="1" id="11" name="Mithril Sword">
    <Texture x ="2" y="0">
      <FileName>itemsEmbed</FileName>
      <Animated />
    </Texture>
  </Object>
</Objects>